qdune/__init__.py
qdune/qdune.py
qdune/test.py
qdune/testdata/info.csv
qdune/testdata/xyz/survey5.txt
qdune/testdata/xyz/survey6.txt
qdune/testdata/xyz/survey7.txt
qdune/testdata/xyz/survey8.txt
qdune-0.1.6.dist-info/DESCRIPTION.rst
qdune-0.1.6.dist-info/METADATA
qdune-0.1.6.dist-info/RECORD
qdune-0.1.6.dist-info/WHEEL
qdune-0.1.6.dist-info/metadata.json
qdune-0.1.6.dist-info/top_level.txt
